spotter/__init__.py
spotter/builder/extras/collection/MANIFEST.json
spotter/builder/extras/collection/galaxy.yml
spotter/builder/extras/collection/plugins/callback/spotter.py
spotter/builder/extras/scripts/entrypoint_hook.sh
spotter/client/__init__.py
spotter/client/cli.py
spotter/client/utils.py
spotter/client/commands/__init__.py
spotter/client/commands/build.py
spotter/client/commands/clear_config.py
spotter/client/commands/clear_policies.py
spotter/client/commands/config.py
spotter/client/commands/get_config.py
spotter/client/commands/login.py
spotter/client/commands/logout.py
spotter/client/commands/policies.py
spotter/client/commands/register.py
spotter/client/commands/scan.py
spotter/client/commands/set_config.py
spotter/client/commands/set_policies.py
spotter/client/commands/suggest.py
spotter/client/commands/config_commands/__init__.py
spotter/client/commands/config_commands/config_clear.py
spotter/client/commands/config_commands/config_get.py
spotter/client/commands/config_commands/config_set.py
spotter/client/commands/policies_commands/__init__.py
spotter/client/commands/policies_commands/policies_clear.py
spotter/client/commands/policies_commands/policies_set.py
spotter/library/__init__.py
spotter/library/api.py
spotter/library/environment.py
spotter/library/runner.py
spotter/library/storage.py
spotter/library/utils.py
spotter/library/builder/__init__.py
spotter/library/builder/builder.py
spotter/library/builder/utils.py
spotter/library/compat/__init__.py
spotter/library/compat/rich.py
spotter/library/formatting/__init__.py
spotter/library/formatting/choices.py
spotter/library/formatting/json_formatter.py
spotter/library/formatting/junit_formatter.py
spotter/library/formatting/models.py
spotter/library/formatting/sarif_formatter.py
spotter/library/formatting/text_formatter.py
spotter/library/formatting/utils.py
spotter/library/formatting/yaml_formatter.py
spotter/library/parsing/__init__.py
spotter/library/parsing/noqa_comments.py
steampunk_spotter-5.10.0.dist-info/licenses/LICENSE
steampunk_spotter-5.10.0.dist-info/METADATA
steampunk_spotter-5.10.0.dist-info/WHEEL
steampunk_spotter-5.10.0.dist-info/entry_points.txt
steampunk_spotter-5.10.0.dist-info/top_level.txt
steampunk_spotter-5.10.0.dist-info/zip-safe
steampunk_spotter-5.10.0.dist-info/RECORD
