Metadata-Version: 2.4
Name: steampunk-spotter
Version: 5.10.0
Summary: Ansible Playbook Platform that scans, analyzes, enhances, and provides insights for your playbooks.
Home-page: https://spotter.steampunk.si/
Author: XLAB d.o.o.
Author-email: "XLAB d.o.o." <pypi@xlab.si>
Project-URL: Homepage, https://spotter.steampunk.si/
Project-URL: Source Code, https://gitlab.com/xlab-steampunk/steampunk-spotter-client/spotter-cli
Project-URL: Bug Tracker, https://gitlab.com/xlab-steampunk/steampunk-spotter-client/spotter-cli/-/issues
Project-URL: Documentation, https://spotter.steampunk.si/docs/
Project-URL: Changelog, https://gitlab.com/xlab-steampunk/steampunk-spotter-client/spotter-cli/-/blob/main/CHANGELOG.txt
Keywords: ansible,automation,spotter,scanner,quality,playbook,steampunk
Classifier: Development Status :: 4 - Beta
Classifier: Environment :: Console
Classifier: Intended Audience :: Developers
Classifier: Intended Audience :: System Administrators
Classifier: Intended Audience :: Science/Research
Classifier: Intended Audience :: Information Technology
Classifier: License :: OSI Approved :: Apache Software License
Classifier: Operating System :: POSIX
Classifier: Programming Language :: Python
Classifier: Programming Language :: Python :: 3
Classifier: Programming Language :: Python :: 3.7
Classifier: Programming Language :: Python :: 3.8
Classifier: Programming Language :: Python :: 3.9
Classifier: Programming Language :: Python :: 3.10
Classifier: Programming Language :: Python :: 3.11
Classifier: Programming Language :: Python :: 3.12
Classifier: Topic :: Software Development
Classifier: Topic :: Software Development :: Bug Tracking
Classifier: Topic :: Software Development :: Quality Assurance
Classifier: Topic :: Software Development :: Testing
Classifier: Topic :: Software Development :: Libraries
Classifier: Topic :: Software Development :: Libraries :: Python Modules
Classifier: Framework :: Ansible
License-File: LICENSE
Requires-Dist: ruamel.yaml>=0.17.22
Requires-Dist: requests
Requires-Dist: colorama
Requires-Dist: pydantic>=2
Requires-Dist: detect-secrets
Requires-Dist: rich>=10.2.0
Provides-Extra: build
Requires-Dist: ansible-builder; extra == "build"
Requires-Dist: ansible-core; extra == "build"
Dynamic: license-file
